{"cameraMode":{"drawMode":0,"name":"Shaded","section":"Shading Mode"},"sceneLighting":true,"audioPlay":false,"sceneViewState":{"showFog":true,"showMaterialUpdate":false,"showSkybox":true,"showFlares":true,"showImageEffects":true,"showParticleSystems":true,"showVisualEffectGraphs":true,"m_FxEnabled":true},"in2DMode":false,"pivot":{"x":19.387250900268556,"y":8.378338813781739,"z":-7.340317726135254},"rotation":{"x":0.03248428925871849,"y":0.9539368748664856,"z":-0.11212246119976044,"w":0.2763754427433014},"size":5.994579315185547,"orthographic":false}